pm/markdown/__about__.py
pm/markdown/__init__.py
pm_markdown-0.1.0.dist-info/METADATA
pm_markdown-0.1.0.dist-info/WHEEL
pm_markdown-0.1.0.dist-info/licenses/LICENSE.txt
pm_markdown-0.1.0.dist-info/RECORD
