Metadata-Version: 2.1
Name: pm-markdown
Version: 0.1.0
Project-URL: Documentation, https://github.com/TruthfulTechnology/pm-markdown#readme
Project-URL: Issues, https://github.com/TruthfulTechnology/pm-markdown/issues
Project-URL: Source, https://github.com/TruthfulTechnology/pm-markdown
Author-email: Trey Hunner <trey@pythonmorsels.com>
License-Expression: MIT
License-File: LICENSE.txt
Classifier: Development Status :: 4 - Beta
Classifier: Programming Language :: Python
Classifier: Programming Language :: Python :: 3.7
Classifier: Programming Language :: Python :: 3.8
Classifier: Programming Language :: Python :: 3.9
Classifier: Programming Language :: Python :: 3.10
Classifier: Programming Language :: Python :: Implementation :: CPython
Classifier: Programming Language :: Python :: Implementation :: PyPy
Requires-Python: >=3.7
